{
  "Arsenal FC": 2553.84,
  "FC Bayern Munchen": 2534.74,
  "Manchester City": 2522.2,
  "Liverpool FC": 2468.95,
  "FC Barcelona": 2456.59,
  "Manchester United": 2451.62,
  "Inter Milan": 2418.64,
  "Chelsea FC": 2409.48,
  "Juventus Torino": 2393.84,
  "Paris Saint-Germain": 2389.93,
  "Como Calcio": 2372.86,
  "RB Leipzig": 2368.24,
  "Borussia Dortmund": 2358.69,
  "Aston Villa": 2349.0,
  "AC Milan": 2348.74,
  "Brighton & Hove Albion": 2338.8,
  "Real Madrid": 2335.93,
  "Sporting Lisboa": 2330.92,
  "1899 Hoffenheim": 2329.32,
  "Brentford FC": 2324.88,
  "VfB Stuttgart": 2324.78,
  "Atletico Madrid": 2322.27,
  "Newcastle United": 2317.68,
  "Nottingham Forest": 2317.23,
  "Bayer Leverkusen": 2316.27,
  "SSC Napoli": 2315.34,
  "FC Porto": 2302.64,
  "Leeds United": 2299.03,
  "AFC Bournemouth": 2298.9,
  "AS Roma": 2298.86,
  "Fulham FC": 2294.66,
  "Benfica Lisboa": 2291.38,
  "Atalanta Bergamo": 2279.02,
  "Everton FC": 2267.06,
  "Crystal Palace": 2267.05,
  "Villarreal CF": 2255.2,
  "Galatasaray": 2254.17,
  "RC Lens": 2250.18,
  "AEK Athens": 2249.2,
  "West Ham United": 2248.07,
  "Olympique Marseille": 2245.0,
  "Tottenham Hotspur": 2240.74,
  "Olympiakos Piraeus": 2232.07,
  "PSV Eindhoven": 2224.15,
  "Betis Sevilla": 2221.53,
  "Fenerbahce": 2220.45,
  "FC Brugge": 2215.53,
  "Besiktas": 2213.38,
  "OSC Lille": 2213.09,
  "FSV Mainz 05": 2212.65,
  "Athletic Bilbao": 2208.07,
  "Real Sociedad": 2207.84,
  "Werder Bremen": 2206.09,
  "Bologna FC": 2205.89,
  "FC Midtjylland": 2202.94,
  "Monchengladbach": 2202.41,
  "Union Saint-Gilloise": 2200.15,
  "SC Freiburg": 2195.46,
  "Sunderland FC": 2195.03,
  "Eintracht Frankfurt": 2193.49,
  "Middlesbrough FC": 2192.54,
  "Sporting Braga": 2192.36,
  "Zenit St. Petersburg": 2189.72,
  "AS Monaco": 2188.94,
  "PAOK Saloniki": 2185.57,
  "Dinamo Zagreb": 2184.36,
  "1. FC Koln": 2183.86,
  "Ipswich Town": 2183.55,
  "Racing Strasbourg": 2183.24,
  "Lazio Roma": 2182.35,
  "1. FC Union Berlin": 2176.25,
  "Coventry City": 2175.97,
  "Wolverhampton Wanderers": 2174.68,
  "Celta de Vigo": 2174.05,
  "US Sassuolo Calcio": 2173.7,
  "Slavia Praha": 2173.12,
  "Rayo Vallecano": 2172.26,
  "FC Augsburg": 2166.46,
  "Stade Rennes": 2165.69,
  "Hammarby IF": 2163.95,
  "Olympique Lyon": 2160.73,
  "Crvena Zvezda Belgrade": 2154.23,
  "Genoa FC": 2153.54,
  "Viking Stavanger": 2152.47,
  "FC Schalke 04": 2150.2,
  "Getafe CF": 2149.89,
  "Hamburger SV": 2149.04,
  "SC Paderborn 07": 2147.9,
  "Hannover 96": 2147.62,
  "Sevilla FC": 2147.23,
  "AC Fiorentina": 2146.36,
  "Aarhus GF": 2146.14,
  "FC Twente Enschede": 2142.55,
  "Girona FC": 2140.52,
  "CA Osasuna": 2138.18,
  "Espanyol Barcelona": 2135.0,
  "Feyenoord Rotterdam": 2134.14,
  "FC Valencia": 2131.76,
  "Red Bull Salzburg": 2131.37,
  "FK Krasnodar": 2130.84,
  "Mjällby AIF": 2127.97,
  "VfL Wolfsburg": 2127.49,
  "FC St. Pauli": 2126.15,
  "SV Elversberg 07": 2124.95,
  "CD Alaves": 2120.64,
  "FC Copenhagen": 2119.86,
  "Sheffield United": 2114.89,
  "Toulouse FC": 2114.52,
  "BK Häcken": 2113.16,
  "Trabzonspor": 2111.74,
  "Southampton FC": 2110.95,
  "Birmingham City": 2110.34,
  "Djurgardens IF": 2108.97,
  "Ajax Amsterdam": 2108.1,
  "Celtic Glasgow": 2107.38,
  "Tromso IL": 2107.27,
  "Glasgow Rangers": 2107.05,
  "Shakhtar Donezk": 2106.39,
  "Istanbul Basaksehir FK": 2102.82,
  "Torino FC": 2099.51,
  "Burnley FC": 2099.06,
  "Hertha BSC Berlin": 2096.87,
  "Ludogorets Razgrad": 2096.57,
  "AZ Alkmaar": 2095.28,
  "Udinese Calcio": 2094.45,
  "KRC Genk": 2093.94,
  "SSC Venezia": 2090.95,
  "Spartak Moskva": 2089.78,
  "Parma Calcio": 2089.07,
  "FK Viktoria Plzen": 2088.27,
  "SV Darmstadt 98": 2087.86,
  "RCD Mallorca": 2087.36,
  "Lincoln City": 2086.9,
  "Elche CF": 2086.44,
  "Norwich City": 2085.56,
  "VfL Bochum": 2084.78,
  "Gais Goteborg": 2083.77,
  "Konyaspor": 2083.46,
  "Fortuna Dusseldorf": 2083.14,
  "Levski Sofia": 2081.04,
  "Panathinaikos": 2077.69,
  "Arminia Bielefeld": 2076.5,
  "IFK Goteborg": 2075.66,
  "Malmo FF": 2073.6,
  "NEC Nijmegen": 2073.52,
  "Goztepe Izmir": 2073.39,
  "Cardiff City": 2071.61,
  "Sparta Praha": 2070.4,
  "Hapoel Beer Sheva": 2069.25,
  "Kocaelispor": 2068.91,
  "OGC Nice": 2068.68,
  "VV St. Truiden": 2068.59,
  "Stade Brest": 2068.07,
  "1. FC Magdeburg": 2068.01,
  "SK Brann Bergen": 2066.45,
  "US Lecce": 2065.6,
  "Millwall FC": 2064.96,
  "LASK Linz": 2064.1,
  "Lillestrom SK": 2063.61,
  "Rakow Czestochowa": 2063.0,
  "Real Oviedo": 2062.97,
  "Ferencvaros Budapest": 2062.84,
  "Viborg FF": 2062.32,
  "Cagliari Calcio": 2062.01,
  "FC Nordsjälland": 2061.21,
  "Lech Poznan": 2060.3,
  "CSKA Moskva": 2058.68,
  "Brondby IF": 2058.63,
  "Alanyaspor": 2055.59,
  "HNK Hajduk Split": 2053.28,
  "UD Levante Valencia": 2053.22,
  "Hellas Verona": 2052.82,
  "IK Sirius FK": 2052.41,
  "Dinamo Moskva": 2050.64,
  "Swansea City": 2048.78,
  "Pisa Calcio": 2048.67,
  "Slovan Bratislava": 2048.65,
  "Wrexham FC": 2047.7,
  "1. FC Nurnberg": 2047.61,
  "Lokomotiv Moskva": 2047.53,
  "Caykur Rizespor": 2046.85,
  "AIK Solna": 2046.47,
  "CD Castellon": 2046.44,
  "Samsunspor": 2046.16,
  "1. FC Heidenheim": 2045.47,
  "Watford FC": 2045.45,
  "FC Thun": 2043.89,
  "Bolton Wanderers": 2042.41,
  "Holstein Kiel": 2041.62,
  "SC Charleroi": 2040.45,
  "CS Universitatea Craiova": 2039.24,
  "Inter Turku": 2037.93,
  "FC Famalicao": 2036.39,
  "FC St. Gallen": 2035.1,
  "RSC Anderlecht": 2034.72,
  "SonderjyskE": 2034.59,
  "Molde FK": 2032.62,
  "FK Karabakh Agdam": 2032.33,
  "Dynamo Dresden": 2031.97,
  "FC Utrecht": 2029.69,
  "Portsmouth FC": 2029.11,
  "Dinamo Kiev": 2027.51,
  "Paris FC": 2026.89,
  "Heart of Midlothian": 2026.61,
  "Gil Vicente": 2025.37,
  "West Bromwich Albion": 2025.27,
  "Young Boys Bern": 2025.11,
  "FC Nantes": 2025.0,
  "SSD Monza 1912": 2023.77,
  "US Cremonese": 2023.31,
  "Leicester City": 2022.56,
  "Le Havre AC": 2022.14,
  "Derby County": 2021.57,
  "IF Elfsborg": 2020.32,
  "Vitoria Guimaraes": 2018.69,
  "1. FC Kaiserslautern": 2018.09,
  "FC Lorient": 2017.12,
  "AC Lugano": 2016.35,
  "Borac Banja Luka": 2016.32,
  "Hansa Rostock": 2014.16,
  "AJ Auxerre": 2013.34,
  "Rapid Wien": 2013.12,
  "Steaua Bukarest": 2012.7,
  "FC Motherwell": 2012.33,
  "Bristol City": 2010.88,
  "Kalmar FF": 2010.5,
  "Sturm Graz": 2009.87,
  "Jagiellonia Bialystok": 2009.74,
  "Servette FC": 2009.38,
  "CSKA Sofia": 2008.91,
  "Gornik Zabrze": 2008.77,
  "FC Sion": 2007.12,
  "FC Basel": 2005.99,
  "Ilves Tampere": 2005.45,
  "Preußen Munster": 2005.33,
  "AE Paphos": 2004.92,
  "Maccabi Tel Aviv": 2004.85,
  "Odense BK": 2004.85,
  "SC Heerenveen": 2002.9,
  "Vitoria Guimaraes SC": 2002.78,
  "Randers FC": 2002.4,
  "US Palermo": 2002.28,
  "SC Verl": 2001.81,
  "Stockport County": 2000.71,
  "FC Groningen": 2000.05,
  "Cercle Brugge": 1998.18,
  "Erzurum BB Spor": 1995.78,
  "KAA Gent": 1994.57,
  "Västeras SK FK": 1994.15,
  "Omonia Nikosia": 1993.75,
  "Widzew Lodz": 1993.51,
  "Amedspor": 1992.72,
  "Santa Clara": 1992.12,
  "SV Ried": 1990.85,
  "AEK Larnaca": 1990.19,
  "York City": 1990.14,
  "Legia Warszawa": 1990.09,
  "FC Luzern": 1988.8,
  "Huddersfield Town": 1988.45,
  "FC Lausanne Sport": 1987.88,
  "Genclerbirligi": 1987.39,
  "Modena FC": 1987.22,
  "Austria Wien": 1985.82,
  "Degerfors IF": 1985.31,
  "HJK Helsinki": 1984.91,
  "Stoke City": 1984.39,
  "SV Zulte-Waregem": 1984.18,
  "Plymouth Argyle": 1983.74,
  "Estoril Praia": 1981.86,
  "Bradford City": 1981.78,
  "Sparta Rotterdam": 1981.62,
  "Hull City": 1981.24,
  "NK Rijeka": 1981.17,
  "Gyori ETO FC": 1980.08,
  "Wycombe Wanderers": 1978.96,
  "SCO Angers": 1978.32,
  "Aris Saloniki": 1978.2,
  "Aris Limassol": 1978.08,
  "FK Slovan Liberec": 1978.03,
  "Eintracht Braunschweig": 1977.32,
  "Erokspor AS": 1977.03,
  "Maccabi Haifa": 1976.61,
  "Blackburn Rovers": 1975.18,
  "Akhmat Grozny": 1973.99,
  "UD Las Palmas": 1973.72,
  "Luton Town": 1973.63,
  "SCR Altach": 1973.0,
  "Baltika Kaliningrad": 1972.36,
  "Wolfsberger AC": 1971.2,
  "Energie Cottbus": 1969.95,
  "Rosenborg Trondheim": 1968.99,
  "Rot-Weiss Essen": 1967.57,
  "Kayserispor": 1967.11,
  "FC Metz": 1966.6,
  "Beitar Jerusalem": 1966.55,
  "VfL Osnabruck": 1966.35,
  "Polissya Zhitomir": 1966.34,
  "Rapid Bucuresti": 1965.8,
  "Dinamo Bukarest": 1964.51,
  "SK Sigma Olomouc": 1963.85,
  "Queens Park Rangers": 1963.23,
  "AS Saint-Etienne": 1962.99,
  "Stade Reims": 1962.64,
  "Milton Keynes Dons": 1962.34,
  "KVC Westerlo": 1962.2,
  "Frosinone Calcio": 1961.13,
  "Karlsruher SC": 1961.07,
  "Apoel Nikosia": 1959.29,
  "Cambridge United": 1958.57,
  "1. FC Saarbrucken": 1958.03,
  "NK Celje": 1956.82,
  "SD Eibar": 1956.57,
  "SV Meppen": 1953.51,
  "MSV Duisburg": 1953.45,
  "Raal La Louviere": 1953.16,
  "Hapoel Tel Aviv": 1953.01,
  "Nacional Madeira": 1951.99,
  "Racing Santander": 1951.17,
  "Apollon Limassol": 1951.16,
  "Lyngby BK": 1950.84,
  "Sandefjord Fotball": 1950.09,
  "Pogon Szczecin": 1950.02,
  "Kasimpasa Istanbul": 1949.86,
  "Sabah FK": 1949.68,
  "FK Jablonec 97": 1949.41,
  "CFR Cluj": 1949.07,
  "IF Brommapojkarna": 1948.55,
  "KV Mechelen": 1947.89,
  "Banik Ostrava": 1947.86,
  "Blau-Weiss Linz": 1947.41,
  "Oud Heverlee Leuven": 1947.11,
  "Lechia Gdansk": 1944.8,
  "Go Ahead Eagles": 1944.66,
  "Deportivo La Coruna": 1944.55,
  "FC Kairat Almaty": 1944.46,
  "Korona Kielce": 1943.6,
  "TSV 1860 Munchen": 1943.37,
  "FK Astana": 1943.22,
  "IFK Norrkoping FK": 1943.18,
  "Antalyaspor": 1940.93,
  "Preston North End": 1940.28,
  "Hibernian Edinburgh": 1940.24,
  "NK Maribor": 1940.12,
  "UD Almeria": 1937.95,
  "WSG Tirol": 1936.22,
  "Valerenga Oslo": 1934.93,
  "Royal Antwerp": 1934.57,
  "Corum FK": 1934.57,
  "Grazer AK": 1934.27,
  "FK Rostov": 1934.09,
  "NAC Breda": 1934.01,
  "Radomiak Radom": 1933.88,
  "Rubin Kazan": 1933.76,
  "Zrinjski Mostar": 1933.53,
  "KFUM-Kam. Oslo": 1932.65,
  "Oxford United": 1932.16,
  "DAC Dunajska Streda": 1931.91,
  "Cracovia Krakow": 1930.39,
  "Stevenage FC": 1929.9,
  "TSV Hartberg": 1929.87,
  "Piast Gliwice": 1929.67,
  "Levadiakos": 1929.59,
  "Tobol Kostanay": 1929.45,
  "FK Riga": 1928.25,
  "Charlton Athletic": 1926.5,
  "Rochdale AFC": 1925.09,
  "Standard Liege": 1924.17,
  "Gazisehir Gaziantep FK": 1923.87,
  "Doncaster Rovers": 1921.78,
  "FC Viktoria Koln": 1921.38,
  "Vardar Skopje": 1920.87,
  "Stormvogels/Telstar": 1920.62,
  "AC Troyes": 1920.22,
  "AC Oulu": 1920.03,
  "Atromitos Athinon": 1919.82,
  "LNZ Cherkasy": 1919.37,
  "FC Hradec Kralove": 1918.38,
  "Universitatea Cluj": 1918.16,
  "FC Arouca": 1918.09,
  "Grasshoppers Zurich": 1917.8,
  "Fredrikstad FK": 1916.9,
  "Falkirk FC": 1916.87,
  "Barnet FC": 1916.54,
  "Vikingur Reykjavik": 1916.49,
  "FC Spartak Trnava": 1915.4,
  "Kauno Zalgiris": 1915.3,
  "Kongsvinger IL": 1915.18,
  "CD Tenerife": 1914.92,
  "FC Alverca": 1914.22,
  "Malaga CF": 1913.92,
  "Moreirense FC": 1913.42,
  "Bohemians 1905": 1913.38,
  "CSKA 1948 Sofia": 1913.13,
  "FC Admira Wacker Modling": 1912.78,
  "NK Osijek": 1912.66,
  "Ural Ekaterinburg": 1912.58,
  "Wisla Krakow": 1912.55,
  "Alemannia Aachen": 1911.77,
  "FC Ingolstadt 04": 1911.34,
  "Excelsior Rotterdam": 1911.28,
  "SpVgg Greuther Furth": 1910.55,
  "Cordoba CF": 1909.4,
  "ADO Den Haag": 1909.16,
  "Mansfield Town": 1908.85,
  "FC Catanzaro": 1908.85,
  "Paks SE": 1907.79,
  "Wigan Athletic": 1907.72,
  "Motor Lublin": 1907.41,
  "NK Slaven Koprivnica": 1906.13,
  "Dinamo Makhachkala": 1905.75,
  "Burgos CF": 1905.09,
  "SK Beveren": 1905.09,
  "Real Valladolid": 1904.99,
  "Vejle BK": 1904.84,
  "Metalist 1925 Kharkiv": 1904.46,
  "Orgryte IS": 1904.37,
  "Jahn Regensburg": 1903.87,
  "Notts County": 1903.68,
  "Silkeborg IF": 1903.26,
  "CD Tondela": 1902.74,
  "FC Zwolle": 1902.55,
  "Sporting Gijon": 1901.99,
  "SpVgg Unterhaching": 1900.76,
  "GKS Katowice": 1900.37,
  "Burton Albion": 1900.15,
  "SV Wehen Wiesbaden": 1899.93,
  "Osters IF": 1899.8,
  "FC Fredericia": 1899.6,
  "FCV Dender EH": 1898.44,
  "Partizan Belgrade": 1898.1,
  "Granada CF": 1897.93,
  "FC Stockholm Internazionale": 1897.88,
  "EA Guingamp": 1897.69,
  "Vojvodina Novi Sad": 1897.24,
  "Aalborg BK": 1894.99,
  "Chesterfield FC": 1894.43,
  "Maritimo Funchal": 1894.19,
  "FC Sudtirol Bolzano": 1894.14,
  "Aarhus Fremad": 1893.93,
  "Fatih Karagumruk": 1893.27,
  "FC Dila Gori": 1892.7,
  "1. FC Lokomotive Leipzig": 1892.66,
  "Bursaspor": 1892.53,
  "Halmstads BK": 1892.43,
  "NK Koper": 1892.27,
  "Sampdoria Genoa": 1891.95,
  "AC Horsens": 1891.43,
  "Andorra CF": 1891.01,
  "Puskas FC": 1890.68,
  "Salford City FC": 1890.61,
  "AFC Wimbledon": 1890.1,
  "Barnsley FC": 1890.01,
  "NK Lokomotiva Zagreb": 1889.79,
  "Cesena FC": 1889.34,
  "Kalamata FC": 1888.45,
  "Casa Pia AC": 1888.42,
  "St. Patricks Athletic": 1888.21,
  "SC Fortuna Koln": 1888.05,
  "CD Leganes": 1887.27,
  "KR Reykjavik": 1886.45,
  "FK Pardubice": 1886.43,
  "HNK Velika Gorica": 1885.64,
  "Hvidovre IF": 1885.47,
  "FC Zurich": 1885.43,
  "IK Start Kristiansand": 1885.34,
  "Igdir FK": 1884.95,
  "FC Iberia 1999": 1884.69,
  "FC Vaduz": 1884.66,
  "MFK Karvina": 1884.31,
  "FK Orenburg": 1884.22,
  "Reading FC": 1883.43,
  "Eyupspor": 1883.16,
  "Aalesunds FK": 1883.09,
  "Wisla Plock": 1881.27,
  "MSK Zilina": 1880.9,
  "Fortuna Sittard": 1880.78,
  "Yelimay Semey": 1880.7,
  "Wurzburger Kickers": 1879.82,
  "Grimsby Town": 1879.78,
  "USL Dunkerque": 1879.58,
  "Heracles Almelo": 1878.65,
  "ZP Sport Podbrezova": 1877.71,
  "AE Larisa": 1877.39,
  "Albacete Balompie": 1877.18,
  "Montpellier HSC": 1876.78,
  "FC Aarau": 1876.52,
  "Borussia Dortmund II": 1876.35,
  "SG Sonnenhof Großaspach": 1874.62,
  "Juve Stabia": 1874.38,
  "Ostersunds FK": 1874.09,
  "Zalaegerszeg TE": 1874.01,
  "IFK Värnamo": 1873.03,
  "Bryne FK": 1872.99,
  "SV Drochtersen/Assel": 1872.94,
  "KI Klaksvik": 1872.93,
  "FK Neftchi Baku": 1872.91,
  "RWD Molenbeek": 1872.88,
  "Leyton Orient": 1872.74,
  "FC Homburg": 1872.09,
  "FK Teplice": 1872.05,
  "Maccabi Petah Tikva": 1871.45,
  "1. FC Brno": 1871.11,
  "Swindon Town": 1870.72,
  "FK Zalgiris Vilnius": 1870.71,
  "Oldham Athletic": 1870.15,
  "Blackpool FC": 1869.76,
  "Ham-Kam": 1869.63,
  "Shamrock Rovers": 1869.62,
  "NK Varazdin": 1869.15,
  "Debrecen VSC": 1868.23,
  "Colchester United": 1868.15,
  "Empoli FC": 1868.05,
  "Muglaspor": 1867.88,
  "Pendikspor": 1867.75,
  "Cherno More Varna": 1867.66,
  "SJK Seinäjoki": 1867.54,
  "LKS Nieciecza": 1867.12,
  "Kahramanmaras Istiklalspor": 1866.85,
  "FC Honka Espoo": 1866.79,
  "VfB Stuttgart II": 1866.67,
  "Zira IK": 1866.05,
  "Ordabasy Shymkent": 1866.05,
  "Hamrun Spartans": 1865.69,
  "SSV Ulm 1846": 1865.67,
  "Academico Viseu": 1865.55,
  "1. FC Slovacko": 1864.28,
  "Zaglebie Lubin": 1863.85,
  "KV Kortrijk": 1863.61,
  "Rio Ave": 1863.29,
  "Dinamo Tirana": 1863.27,
  "FK Aktobe": 1862.87,
  "Carrarese Calcio": 1862.74,
  "Akron Tolyatti": 1862.39,
  "NK Olimpija Ljubljana": 1862.13,
  "1899 Hoffenheim II": 1862.09,
  "Annecy FC": 1861.58,
  "Batman Petrolspor": 1861.45,
  "CF Estrela": 1861.12,
  "FC Carl Zeiss Jena": 1860.91,
  "The New Saints": 1860.65,
  "Le Mans UC 72": 1860.01,
  "Red Star 93": 1859.82,
  "Ujpest Budapest": 1859.66,
  "Southend United": 1859.66,
  "FC Noah": 1859.55,
  "Saint Johnstone FC": 1859.55,
  "Spezia Calcio": 1858.99,
  "Bohemians Dublin": 1858.87,
  "SV Waldhof Mannheim": 1858.67,
  "Exeter City": 1858.45,
  "Panionios": 1857.61,
  "NK Istra 1961 Pula": 1856.85,
  "Karpaty Lviv": 1856.07,
  "FC Arges Pitesti": 1856.03,
  "AE Kifisia FC": 1855.41,
  "Forest Green Rovers": 1854.93,
  "Bromley FC": 1854.73,
  "Boreham Wood FC": 1854.49,
  "Bukovina Chernovtsy": 1852.22,
  "Hillerod Fodbold": 1851.56,
  "RW Oberhausen": 1851.3,
  "FF Jaro Jakobstad": 1850.14,
  "Rodina Moscow": 1850.11,
  "ACS CFC Arges Pitesti": 1850.05,
  "FK Arda Kardzhali": 1849.8,
  "OFI Crete": 1849.41,
  "VfB Oldenburg": 1848.7,
  "Derry City": 1848.3,
  "Peterborough United": 1848.21,
  "Stade Lausanne-Ouchy": 1847.72,
  "Nordic United": 1847.21,
  "FC Zlin": 1846.82,
  "Rotherham United": 1846.09,
  "FC Erzgebirge Aue": 1846.03,
  "PFK Turan Tovuz": 1845.68,
  "Asteras Tripolis": 1845.38,
  "FK Kosice": 1844.76,
  "Shakhtyor Karaganda": 1844.7,
  "Skendija 79 Tetovo": 1844.7,
  "FK Shkendija 79 Tetovo": 1844.47,
  "Varbergs BoIS FC": 1844.42,
  "Real Zaragoza": 1844.24,
  "UTA Batrana Doamna": 1843.99,
  "FC Levadia Tallinna": 1843.87,
  "Stjarnan Gardabaer": 1843.21,
  "Floridsdorfer AC": 1840.73,
  "NK Bravo": 1840.68,
  "Ararat-Armenia": 1840.49,
  "Real Sociedad II": 1840.44,
  "AC Mantova": 1840.26,
  "FC Sheriff Tiraspol": 1840.26,
  "Esbjerg fB": 1840.02,
  "Fakel Voronezh": 1839.89,
  "KIF Kolding": 1839.8,
  "FC Botosani": 1839.61,
  "Pau FC": 1839.57,
  "IA Akranes": 1839.12,
  "SKN St. Polten": 1839.12,
  "SC Bastia": 1837.5,
  "Shelbourne FC": 1836.07,
  "Lyn Oslo": 1835.44,
  "FC KooTeePee Kotka": 1835.2,
  "Breidablik Kopavogur": 1835.04,
  "Leeuwarden Cambuur": 1834.8,
  "Wacker Burghausen": 1834.66,
  "Torpedo Kutaisi": 1833.95,
  "VJS Vantaa": 1832.81,
  "Fleetwood Town": 1832.24,
  "IK Brage": 1831.47,
  "Hapoel Petah Tikva": 1830.84,
  "CD Mirandes": 1830.59,
  "Volos NFC": 1830.47,
  "AFC Fylde": 1830.39,
  "FC Wacker Innsbruck": 1830.33,
  "US Avellino": 1829.95,
  "Bodrumspor": 1829.53,
  "Kristiansund BK": 1829.29,
  "Panaitolikos": 1829.22,
  "Elazigspor": 1828.62,
  "AB Gladsaxe": 1828.56,
  "St. Mirren": 1828.41,
  "Sariyer SK": 1828.28,
  "Anorthosis Famagusta": 1828.13,
  "FC Aberdeen": 1828.05,
  "Krylya Sovetov Samara": 1827.87,
  "FK Vanspor": 1827.66,
  "AD Ceuta": 1827.38,
  "Maccabi Netanya": 1827.19,
  "Varda SE": 1826.88,
  "FC Vizela": 1826.86,
  "Cadiz CF": 1826.62,
  "Zeljeznicar Sarajevo": 1826.47,
  "FK Sarajevo": 1826.28,
  "FK Nizhny Novgorod": 1824.28,
  "Benevento Calcio": 1824.15,
  "Botev Plovdiv": 1824.12,
  "SD Huesca": 1823.7,
  "Diosgyor DVTK": 1823.16,
  "Dinamo Tbilisi": 1823.02,
  "Bandirmaspor": 1822.85,
  "Otelul Galati": 1822.51,
  "Helsingborgs IF": 1821.68,
  "Mlada Boleslav": 1821.03,
  "Nyiregyhazi Spartacus": 1820.72,
  "SCU Torreense": 1820.27,
  "Rigas Futbola Skola": 1819.64,
  "Kolos Kovalivka": 1819.24,
  "Corvinul Hunedoara": 1818.49,
  "1. FC Bocholt": 1818.45,
  "Port Vale": 1818.38,
  "Arka Gdynia": 1818.34,
  "Sivasspor": 1818.22,
  "Virtus Entella": 1817.99,
  "AVS Futebol": 1815.58,
  "Keciorengucu": 1815.58,
  "South Shields": 1815.03,
  "FC Struga Trim-Lum": 1814.07,
  "Yverdon Sport FC": 1814.06,
  "Dundee United": 1813.62,
  "KA Akureyri": 1813.6,
  "Carlisle United": 1812.62,
  "FC Volendam": 1811.87,
  "Rodez AF": 1811.7,
  "Northampton Town": 1810.99,
  "Pescara Calcio": 1810.86,
  "Stabaek IF": 1810.14,
  "SGV Freiberg": 1809.4,
  "Sariyer GK": 1809.28,
  "FV Illertissen": 1808.81,
  "SV Sandhausen": 1808.08,
  "Hallescher FC": 1807.97,
  "1. FC Nurnberg II": 1807.48,
  "SC Austria Lustenau": 1807.43,
  "Falkenbergs FF": 1806.75,
  "Wieczysta Krakow": 1806.74,
  "Walsall FC": 1806.34,
  "SKU Amstetten": 1806.12,
  "Jonkopings Sodra IF": 1805.24,
  "Bristol Rovers": 1805.18,
  "GD Chaves": 1805.11,
  "Crewe Alexandra": 1804.75,
  "Bayern Munchen II": 1804.67,
  "Orebro SK": 1804.6,
  "CS Voluntari": 1804.3,
  "Eintracht Trier": 1803.89,
  "Hammarby TFF": 1803.69,
  "KFCO Beerschot Wilrijk": 1803.62,
  "Gillingham FC": 1803.01,
  "FC Schalke 04 II": 1802.97,
  "FC Felgueiras": 1802.8,
  "FC Phonix Lubeck": 1802.76,
  "Catania Calcio": 1802.48,
  "Calcio Padova": 1802.47,
  "SC Farense": 1802.45,
  "Cultural Leonesa": 1801.72,
  "Torpedo Moskva": 1801.54,
  "Zorya Lugansk": 1801.14,
  "Clermont Foot": 1801.05,
  "SK Artis Brno": 1800.11,
  "IK Oddevold": 1799.76,
  "1. FSV Mainz 05 II": 1799.22,
  "Slask Wroclaw": 1798.83,
  "Strommen IF": 1798.43,
  "Differdange FC 03": 1797.16,
  "Uniao Leiria": 1797.03,
  "Iraklis FC": 1797.01,
  "FC Dundee": 1796.83,
  "Ranheim Trondheim": 1796.7,
  "Egnatia Rrogozhine": 1796.65,
  "Sandvikens IF": 1796.28,
  "Hessen Kassel": 1796.07,
  "Benfica Lisboa II": 1795.78,
  "Sandnes Ulf": 1795.78,
  "Landskrona BoIS": 1795.72,
  "Pyunik Yerevan": 1795.55,
  "Sportfreunde Siegen": 1795.07,
  "AEL Limassol FC": 1793.96,
  "Petrolul Ploiesti": 1793.78,
  "VSG Altglienicke": 1793.39,
  "Kidderminster Harriers": 1793.37,
  "AS Nancy Lorraine": 1792.45,
  "Farul Constanta": 1791.7,
  "Kickers Emden": 1791.07,
  "Budapest Honved": 1790.96,
  "MTK Budapest": 1790.64,
  "Fram Reykjavik": 1790.28,
  "AFC Hermannstadt": 1790.17,
  "FC Roskilde": 1789.9,
  "Cukaricki Belgrade": 1789.8,
  "CE Sabadell": 1789.65,
  "Lokomotiv Plovdiv": 1789.29,
  "SSV Jeddeloh": 1788.94,
  "Scunthorpe United": 1787.93,
  "FH Hafnarfjordur": 1787.89,
  "FK Sochi": 1787.59,
  "Kryvbas Krivoj Rog": 1786.88,
  "Mus 1984 Musspor": 1786.32,
  "Miedz Legnica": 1786.0,
  "FC Kilmarnock": 1785.8,
  "Vasas Budapest": 1785.61,
  "KF Ballkani": 1785.22,
  "Atletico Madrid II": 1785.07,
  "Spartak Kostroma": 1784.53,
  "UD Ibiza": 1783.91,
  "Hobro IK": 1783.47,
  "Vicenza Virtus": 1783.42,
  "Stuttgarter Kickers": 1783.16,
  "IFK Mariehamn": 1782.64,
  "FK Kaspyi Aktau": 1782.43,
  "Floriana FC": 1782.38,
  "FSV Frankfurt": 1782.13,
  "Willem II Tilburg": 1781.45,
  "Hapoel Haifa": 1780.76,
  "1. FC Magdeburg II": 1780.28,
  "Aliaga Futbol": 1780.26,
  "FC Astoria Walldorf": 1779.93,
  "Lokomotiv Sofia": 1779.76,
  "Almere City": 1779.73,
  "FC Winterthur": 1779.06,
  "ASK Voitsberg": 1778.89,
  "De Graafschap": 1778.69,
  "Polonia Warszawa": 1778.68,
  "Dijon FC": 1777.97,
  "Sepsi OSK Sfantu Gheorghe": 1777.78,
  "SSC Bari": 1777.29,
  "US Boulogne": 1775.14,
  "FSV Zwickau": 1774.23,
  "POT Iraklis 1908 FC": 1773.89,
  "SFC Opava": 1773.85,
  "Backa Topola": 1773.47,
  "Radnicki 1923 Kragujevac": 1773.34,
  "Egersunds IK": 1773.2,
  "Linfield FC": 1772.94,
  "Sporting Lisboa II": 1772.01,
  "Shrewsbury Town": 1771.78,
  "Rot-Weiss Erfurt": 1771.78,
  "FC Gutersloh 2000": 1771.77,
  "Omonia Aradippou": 1771.28,
  "Lommel SK": 1770.99,
  "Istanbulspor": 1770.26,
  "KS Vllaznia Shkoder": 1770.18,
  "FC Haka Valkeakoski": 1769.89,
  "Aldershot Town": 1769.07,
  "Arsenal Tula": 1768.74,
  "Ljungskile SK": 1768.15,
  "FK Dukla Praha": 1768.1,
  "CS Petrocub": 1768.08,
  "Partick Thistle": 1767.83,
  "FC Flora Tallinna": 1767.63,
  "Coleraine FC": 1767.38,
  "Velez Mostar": 1765.74,
  "Crawley Town": 1765.61,
  "TSV Steinbach": 1764.94,
  "KF Drita": 1764.84,
  "AD Alcorcon": 1764.55,
  "CD Feirense": 1764.41,
  "Worthing FC": 1764.39,
  "IF Gnistan Helsinki": 1763.87,
  "SC Paderborn 07 II": 1763.54,
  "1. FC Koln II": 1763.3,
  "MFK Skalica": 1763.29,
  "AC Reggiana": 1763.26,
  "SC Freiburg II": 1763.13,
  "FC Rouen 1899": 1762.78,
  "Stade Lavallois": 1762.19,
  "Thor Akureyri": 1762.01,
  "Hapoel Ironi Kiryat Shmona": 1761.95,
  "Niki Volou": 1761.8,
  "Barakaldo CF": 1761.62,
  "Sportfreunde Lotte": 1761.24,
  "KamAZ N.Chelny": 1760.58,
  "Sporting Hasselt FC": 1760.53,
  "FK Novi Pazar": 1760.41,
  "SK Kladno": 1760.3,
  "VPS Vaasa": 1760.1,
  "Leixoes Matosinhos": 1759.91,
  "Inegolspor": 1759.74,
  "Patro Eisden": 1759.55,
  "AS Trencin": 1759.51,
  "Sakaryaspor Adapazari": 1759.41,
  "Athletic Bilbao II": 1758.18,
  "Glentoran FC": 1758.07,
  "Manisa BBSK": 1757.88,
  "SG Barockstadt Fulda": 1757.67,
  "Rotor Volgograd": 1757.57,
  "Lusitania FC Lourosa": 1757.53,
  "FC Liefering": 1757.48,
  "Hannover 96 II": 1757.4,
  "Racing Club Ferrol": 1757.37,
  "LKS Lodz": 1757.05,
  "Neuchatel Xamax": 1756.67,
  "OFK Belgrade": 1755.51,
  "Hartlepool United FC": 1754.21,
  "Epicenter Dunaivtsi": 1754.13,
  "SpVgg Greuther Furth II": 1753.48,
  "Tromsdalen UIL": 1753.41,
  "AC Arezzo": 1752.76,
  "Irtysh Pavlodar": 1752.28,
  "MFK Zemplin Michalovce": 1752.1,
  "FK Kyzylzhar Petropavlovsk": 1750.72,
  "FC Urartu": 1749.68,
  "Adana 01 FK": 1749.13,
  "Dukla Banska Bystrica": 1748.83,
  "Grenoble Foot 38": 1748.75,
  "GIF Sundsvall": 1748.66,
  "Zamora CF": 1748.12,
  "KFC Komarno": 1748.12,
  "Ebbsfleet United": 1748.03,
  "Hapoel Jerusalem": 1747.28,
  "Slavia Sofia": 1746.43,
  "TSV Havelse": 1746.36,
  "CD Lugo": 1746.2,
  "Ankaraspor": 1746.19,
  "Vasalunds IF": 1746.05,
  "Dundalk FC": 1745.85,
  "CD Eldense": 1745.41,
  "Teuta Durres": 1745.41,
  "FK Livyi Bereg Kiev": 1744.88,
  "VPS Vaasa II": 1744.65,
  "FK Zeleznicar Pancevo": 1744.35,
  "Barrow AFC": 1744.33,
  "Veres Rivne": 1744.0,
  "Mardin 1969 Spor": 1743.56,
  "FC Atyrau": 1743.09,
  "Digenis Ypsonas": 1743.08,
  "Ruch Chorzow": 1742.8,
  "1.FC Tatran Presov": 1741.89,
  "B 93 Copenhagen": 1741.86,
  "Chemnitzer FC": 1741.71,
  "Accrington Stanley": 1741.57,
  "SD Ponferradina": 1740.96,
  "Real Murcia": 1740.74,
  "Sogndal IL": 1740.11,
  "Real Madrid II": 1740.01,
  "Panseraikos": 1739.97,
  "MFK Ruzomberok": 1739.72,
  "DJK Vilzing": 1739.45,
  "IBV Vestmannaeyjar": 1739.26,
  "Roda Kerkrade": 1739.18,
  "Hercules CF": 1739.11,
  "Macclesfield FC": 1738.86,
  "FK Standard Sumgayit": 1738.83,
  "Ankaragucu": 1738.7,
  "Umraniyespor": 1738.1,
  "FC Penafiel": 1738.07,
  "Hamburger SV II": 1737.92,
  "Sheffield Wednesday": 1737.4,
  "Utsiktens BK": 1736.87,
  "RKC Waalwijk": 1736.81,
  "SV Rodinghausen": 1735.95,
  "Slavia Praha II": 1735.86,
  "Ethnikos Achnas": 1735.28,
  "Sanliurfaspor": 1735.22,
  "FK Chelyabinsk": 1734.6,
  "Norrby IF": 1734.49,
  "Neftekhimik Nizhnekamsk": 1734.35,
  "FC Crotone": 1734.17,
  "FC Zimbru Chisinau": 1733.84,
  "Radnicki Nis": 1733.78,
  "TSV Aubstadt": 1733.55,
  "Pontevedra CF": 1733.27,
  "Academica Coimbra": 1732.57,
  "AF Elbasani": 1732.42,
  "Moss FK": 1732.36,
  "FC Dordrecht": 1732.3,
  "FC Ashdod": 1732.28,
  "Botev Vratsa": 1732.1,
  "Greifswalder FC": 1731.19,
  "Amiens SC": 1730.75,
  "Cheltenham Town": 1730.1,
  "VfL Bochum II": 1730.03,
  "Boluspor": 1729.78,
  "Polonia Bytom": 1729.49,
  "Umeå FC": 1728.76,
  "Galway United": 1728.72,
  "FC Cartagena": 1728.62,
  "FC Porto II": 1727.93,
  "AD Fafe": 1727.64,
  "KF Llapi": 1727.52,
  "Chelmsford City": 1727.51,
  "Bnei Yehuda": 1727.18,
  "Boston United": 1727.14,
  "Celta de Vigo II": 1726.69,
  "NSI Runavik": 1726.64,
  "KSC Lokeren": 1726.24,
  "Livingston FC": 1726.11,
  "ETSV Weiche Flensburg": 1725.43,
  "Milsami Orhei": 1725.36,
  "KF Gjilani": 1725.07,
  "Kaisar Kyzylorda": 1724.83,
  "Valletta FC": 1724.74,
  "Salernitana Calcio 1919": 1724.7,
  "Valur Reykjavik": 1724.35,
  "Ascoli Picchio": 1724.04,
  "Solihull Moors FC": 1723.97,
  "FC Okzhetpes": 1723.85,
  "Araz Nakhchivan PFK": 1723.66,
  "PAE Anagennisi Karditsas 1904": 1723.64,
  "Larne FC": 1722.16,
  "Maidenhead United": 1721.99,
  "FK MAS Taborsko": 1721.25,
  "Connahs Quay": 1721.24,
  "CE Europa": 1720.26,
  "FK Csikszereda Miercurea Ciuc": 1720.17,
  "Olympiakos Nikosia": 1719.74,
  "Tranmere Rovers": 1719.74,
  "Zhetysu Taldykorgan": 1719.39,
  "Ihoud Bnei Sakhnin": 1719.16,
  "Hässleholms IF": 1718.65,
  "SKA Energiya Khabarovsk": 1717.95,
  "Maidstone United": 1716.65,
  "Banik Ostrava II": 1716.28,
  "Monchengladbach II": 1715.92,
  "Inverness Caledonian Thistle": 1715.45,
  "HB Koge": 1715.43,
  "CSA Steaua Bukarest": 1715.22,
  "Kickers Offenbach": 1715.06,
  "Volga Ulyanovsk": 1713.94,
  "FC Wil": 1713.55,
  "PFC Oleksandria": 1713.27,
  "RFC Liege": 1712.93,
  "US Orleans": 1712.75,
  "AS Eupen": 1712.27,
  "AFC Telford United": 1712.19,
  "Sutton United": 1711.84,
  "Pogon Grodzisk Mazowiecki": 1711.81,
  "MFK Usti Nad Labem": 1711.8,
  "Antequera CF": 1711.72,
  "Chrobry Glogow": 1711.61,
  "Grorud IL": 1711.43,
  "Algeciras CF": 1711.34,
  "Yenisey Krasnoyarsk": 1711.21,
  "Merida AD": 1711.04,
  "Radnik Surdulica": 1711.04,
  "Fylkir Reykjavik": 1710.95,
  "Union Brescia": 1710.78,
  "KF Prishtina": 1710.78,
  "Halifax Town": 1710.69,
  "FK Hegelmann Litauen": 1710.49,
  "Obolon Kiev": 1710.46,
  "Woking FC": 1710.38,
  "FK Tyumen": 1709.84,
  "Kecskemeti TE": 1709.14,
  "Chester FC": 1709.12,
  "1. FC Schweinfurt 05": 1708.91,
  "Unionistas de Salamanca CF": 1708.68,
  "Chernomorets Odessa": 1708.49,
  "SV Babelsberg 03": 1708.15,
  "NK Radomlje": 1707.25,
  "Aluminij Kidricevo": 1707.19,
  "UNA Strassen": 1706.88,
  "Middelfart BK": 1706.67,
  "Villarreal CF II": 1706.66,
  "CF Os Belenenses": 1705.85,
  "TSV Buchbach": 1705.76,
  "Le Puy Foot 43": 1705.63,
  "Alashkert FC": 1705.47,
  "IBV Keflavik": 1705.34,
  "NS Mura": 1705.22,
  "Vitesse Arnheim": 1704.32,
  "Hertha BSC Berlin II": 1001.0,
  "USC Paredes": 1002.0,
  "KF Dukagjini": 1003.0,
  "Werder Bremen II": 1004.0,
  "Harborough Town FC": 1005.0,
  "NK Triglav Kranj": 1006.0,
  "AZ Alkmaar II": 1007.0,
  "FC Sochaux": 1008.0,
  "FK Sileks Kratovo": 1009.0,
  "F 91 Dudelingen": 1010.0,
  "Wealdstone FC": 1011.0,
  "FC Zhenis": 1012.0,
  "BFC Dynamo Berlin": 1013.0,
  "FC Etoile Carouge": 1014.0,
  "Viktoria Zizkov": 1015.0,
  "ND Primorje": 1016.0,
  "JK Nomme Kalju": 1017.0,
  "SK Tirana": 1018.0,
  "FC Flora Paide": 1019.0,
  "Pacos Ferreira": 1020.0,
  "Ironi Tiberias": 1021.0,
  "BFC Preussen Berlin": 1022.0,
  "First Vienna FC 1894": 1023.0,
  "Shamakhi FK": 1024.0,
  "Portimonense SC": 1025.0,
  "Brinje Grosuplje": 1026.0,
  "FC Samgurali Tskaltubo": 1027.0,
  "FK Buducnost Podgorica": 1028.0,
  "Dobrudzha Dobrich": 1029.0,
  "KVV Quick Boys": 1030.0,
  "FK Ulytau Zhezkazgan": 1031.0,
  "Sliema Wanderers": 1032.0,
  "FC Rustavi": 1033.0,
  "Anagennisi Karditsas": 1034.0,
  "NK Vukovar 91": 1035.0,
  "FC Augsburg II": 1036.0,
  "Partizani Tirana": 1037.0,
  "UD Oliveirense": 1038.0,
  "FK Kudrivka": 1039.0,
  "Chindia Targoviste": 1040.0,
  "FK Panevezys": 1041.0,
  "KAA Gent II": 1042.0,
  "Asc Biesheim": 1043.0,
  "Drogheda United": 1044.0,
  "Shinnik Jaroslawl": 1045.0,
  "SM Caen": 1046.0,
  "CSM Resita": 1047.0,
  "Ironi Rishon Lezion": 1048.0,
  "Ourense CF": 1049.0,
  "FC Bihor Oradea": 1050.0,
  "FK Qabala": 1051.0,
  "Torquay United": 1052.0,
  "Chernomorets Novorossiysk": 1053.0,
  "FC ViOn Zlate Moravce": 1054.0,
  "Darlington FC": 1055.0,
  "Chorley FC": 1056.0,
  "FC Hertha Wels": 1057.0,
  "Altai Semey": 1058.0,
  "Stal Rzeszow": 1059.0,
  "Beyoglu Yeni Carsi": 1060.0,
  "FK Transinvest": 1061.0,
  "Trelleborgs FF": 1062.0,
  "CD Teruel": 1063.0,
  "NK Posusje": 1064.0,
  "SPG Wels": 1065.0,
  "SV Austria Salzburg": 1066.0,
  "SD Tarazona": 1067.0,
  "VfB Eichstätt": 1068.0,
  "Odd Grenland": 1069.0,
  "OLS Oulu": 1070.0,
  "Radcliffe Borough": 1071.0,
  "FK Suduva Marijampole": 1072.0,
  "Ayr United": 1073.0,
  "Fortuna Dusseldorf II": 1074.0,
  "Raith Rovers Kirkcaldy": 1075.0,
  "Bonner SC": 1076.0,
  "Dorking Wanderers": 1077.0,
  "CS Gloria 2018": 1078.0,
  "FSV 63 Luckenwalde": 1079.0,
  "FC Den Bosch": 1080.0,
  "Sutjeska Niksic": 1081.0,
  "Siroki Brijeg": 1082.0,
  "Kazincbarcika BSC": 1083.0,
  "Sotra SK": 1084.0,
  "Spalding United": 1085.0,
  "IMT Novi Beograd": 1086.0,
  "Dunav Ruse": 1087.0,
  "Vendsyssel FF": 1088.0,
  "Odra Opole": 1089.0,
  "MS Kiryat Yam": 1090.0,
  "FSV Schoningen": 1091.0,
  "FC Rapperswil-Jona": 1092.0,
  "SpVgg Ansbach 09": 1093.0,
  "Iskenderun FK": 1094.0,
  "Kairat Almaty II": 1095.0,
  "Tvaakers IF": 1096.0,
  "AC Bellinzona": 1097.0,
  "Newport County AFC": 1098.0,
  "Versailles 78 FC": 1099.0,
  "AFC Hornchurch": 1100.0,
  "Tamworth FC": 1101.0,
  "Ilves Tampere II": 1102.0,
  "Wuppertaler SV": 1103.0,
  "Harrogate Town": 1104.0,
  "TuS BW Lohne": 1105.0,
  "VfB Lubeck": 1106.0,
  "CD Arenteiro": 1107.0,
  "Valenciennes FC": 1108.0,
  "SW Bregenz": 1109.0,
  "Altrincham FC": 1110.0,
  "FC Gareji Sagarejo": 1111.0,
  "Stal Mielec": 1112.0,
  "Gimnastic de Tarragona": 1113.0,
  "Unirea Slobozia": 1114.0,
  "Puszcza Niepolomice": 1115.0,
  "Javor Ivanjica": 1116.0,
  "Raufoss Fotball": 1117.0,
  "Pitea IF": 1118.0,
  "Arendal Fotball": 1119.0,
  "Nea Salamina": 1120.0,
  "UMF Njardvik": 1121.0,
  "Gefle IF": 1122.0,
  "Stade Nyonnais": 1123.0,
  "Ross County": 1124.0,
  "Dunfermline AFC": 1125.0,
  "Lusitano Ginasio Clube": 1126.0,
  "HB Torshavn": 1127.0,
  "Arbroath FC": 1128.0,
  "Royal Francs Borains": 1129.0,
  "FC Vysocina Jihlava": 1130.0,
  "Rijnsburgse Boys": 1131.0,
  "Kjelsas Oslo": 1132.0,
  "Marsaxlokk FC": 1133.0,
  "Varzim SC": 1134.0,
  "FK Ufa": 1135.0,
  "FK Auda Riga": 1136.0,
  "Kallithea FC Athen": 1137.0,
  "CP Cacereno": 1138.0,
  "GKS Tychy 71": 1139.0,
  "Guzide Gebzespor": 1140.0,
  "SV Stripfing": 1141.0,
  "Gnistan Ogeli": 1142.0,
  "Ternana Calcio": 1143.0,
  "Hapoel Kfar Saba": 1144.0,
  "SK Sturm Graz II": 1145.0,
  "Inter Turku II": 1146.0,
  "FK Septemvri Sofia": 1147.0,
  "FK Liptovsky Mikulas": 1148.0,
  "Hapoel Kfar Shelem": 1149.0,
  "HK Kopavogur": 1150.0,
  "Næstved BK": 1151.0,
  "CD Mafra": 1152.0,
  "Assyriska FF": 1153.0,
  "Pogon Siedlce": 1154.0,
  "Atletico Clube de Portugal": 1155.0,
  "FK Austria Wien II": 1156.0,
  "AFC Metalul Buzau": 1157.0,
  "Buxton FC": 1158.0,
  "HHC Hardenberg": 1159.0,
  "Morecambe FC": 1160.0,
  "FC Memmingen": 1161.0,
  "Chatham Town": 1162.0,
  "Nuova Cosenza": 1163.0,
  "FC Vlasim": 1164.0,
  "UD Marbella": 1165.0,
  "VV Venlo": 1166.0,
  "FC Fleury 91": 1167.0,
  "AC Trento": 1168.0,
  "RWDM Brussels": 1169.0,
  "Brackley Town": 1170.0,
  "TSV Schwaben Augsburg": 1171.0,
  "Southport FC": 1172.0,
  "Maccabi Bnei Reina": 1173.0,
  "Dagenham & Redbridge": 1174.0,
  "FC Emmen": 1175.0,
  "FC Trollhättan": 1176.0,
  "Enkoping SK": 1177.0,
  "Renaissance Mons 44": 1178.0,
  "Real Aviles": 1179.0,
  "Arsenal Ceska Lipa": 1180.0,
  "FC Arlanda": 1181.0,
  "FC Utrecht II": 1182.0,
  "RAEC Mons": 1183.0,
  "FK Jerv": 1184.0,
  "Arenas Getxo": 1185.0,
  "Kastamonuspor": 1186.0,
  "Nykobing FC": 1187.0,
  "KF Malisheva": 1188.0,
  "TSG Balingen": 1189.0,
  "Chesham United": 1190.0,
  "Bremer SV": 1191.0,
  "Gornik Leczna": 1192.0,
  "Hapoel Ramat Gan": 1193.0,
  "ND Beltinci": 1194.0,
  "Vitoria Guimaraes II": 1195.0,
  "Folkestone Invicta": 1196.0,
  "Beroe Stara Zagora": 1197.0,
  "Jadran LP": 1198.0,
  "SK Austria Klagenfurt": 1199.0,
  "Znicz Pruszkow": 1200.0,
  "Ariana FC": 1201.0,
  "SV Seekirchen": 1202.0,
  "St. Josephs FC": 1203.0,
  "FC Eindhoven": 1204.0,
  "Gateshead FC": 1205.0,
  "FK Liepaja": 1206.0,
  "Juventud Torremolinos CF": 1207.0,
  "NK Nafta Lendava": 1208.0,
  "Kutahyaspor": 1209.0,
  "FC Järfälla": 1210.0,
  "Inter D Escaldes": 1211.0,
  "LASK Linz II": 1212.0,
  "Fehervar FC": 1213.0,
  "FC Rukh Lviv": 1214.0,
  "Tikves Kavadarci": 1215.0,
  "Flamurtari Vlore": 1216.0,
  "Husqvarna FF": 1217.0,
  "CD Guadalajara": 1218.0,
  "Hemel Hempstead Town": 1219.0,
  "Yeovil Town FC": 1220.0,
  "FC St. Pauli II": 1221.0,
  "Imisli FK": 1222.0,
  "Akritas Chlorakas": 1223.0,
  "Spartak Varna": 1224.0,
  "Marko": 1225.0,
  "FK Dziugas": 1226.0,
  "Eskilsminne IF": 1227.0,
  "Eintracht Norderstedt": 1228.0,
  "Waterford United": 1229.0,
  "IF Karlstad": 1230.0,
  "FC Meshakhte Tkibuli": 1231.0,
  "FC Sevilla II": 1232.0,
  "FC Gagra": 1233.0,
  "BSG Chemie Leipzig": 1234.0,
  "Honefoss BK": 1235.0,
  "Hereford FC": 1236.0,
  "Radnik Bijeljina": 1237.0,
  "SC Kriens": 1238.0,
  "Athletic FC United": 1239.0,
  "Scarborough Athletic": 1240.0,
  "Atalanta Bergamo II": 1241.0,
  "Royal Union Tubize Braine": 1242.0,
  "Karlbergs BK": 1243.0,
  "Farnham Town": 1244.0,
  "SK Rapid Wien II": 1245.0,
  "SV Kapfenberg": 1246.0,
  "Zelezarny Trinec": 1247.0,
  "FBK Karlstad": 1248.0,
  "FK Mornar Bar": 1249.0,
  "AFK Chrudim": 1250.0,
  "Vitoria Guimaraes SC B": 1251.0,
  "Afturelding Mosfellsbaer": 1252.0,
  "Club Brugge II": 1253.0,
  "Ängelholms FF": 1254.0,
  "NK Domzale": 1255.0,
  "Hapoel Bueine": 1256.0,
  "Karmiotissa Polemidion": 1257.0,
  "National Sebis": 1258.0,
  "Talavera CF": 1259.0,
  "SpVgg Bayreuth": 1260.0,
  "OFK Petrovac": 1261.0,
  "IF Vestri": 1262.0,
  "Maccabi Herzelia": 1263.0,
  "Atert Bissen": 1264.0,
  "Merthyr Town": 1265.0,
  "Lierse Kempenzonen": 1266.0,
  "Weston Super Mare": 1267.0,
  "Sokol Saratov": 1268.0,
  "Audace Cerignola": 1269.0,
  "Eidsvold TF": 1270.0,
  "KF Drenica Skenderaj": 1271.0,
  "IL Hodd Ulsteinvik": 1272.0,
  "US Concarneau": 1273.0,
  "Ellas Syros": 1274.0,
  "Spal Ferrara 1907": 1275.0,
  "Asane Fotball": 1276.0,
  "Eastleigh FC": 1277.0,
  "De Treffers": 1278.0,
  "Throttur Reykjavik": 1279.0,
  "KuPS Kuopio": 1280.0,
  "Horsham FC": 1281.0,
  "FC Telavi": 1282.0,
  "CSM Slatina": 1283.0,
  "Truro City FC": 1284.0,
  "CA Osasuna II": 1285.0,
  "Oskarshamns AIK": 1286.0,
  "NKP Podhale Nowy Targ": 1287.0,
  "SK Hanacka Slavia Kromeriz": 1288.0,
  "CS Concordia Chiajna": 1289.0,
  "Union Gurten": 1290.0,
  "FK Sloga Doboj": 1291.0,
  "Kings Lynn": 1292.0,
  "FK Banga Gargzdai": 1293.0,
  "Malmin Ponnistajat": 1294.0,
  "Olympiakos Piraeus II": 1295.0,
  "Gebzespor": 1296.0,
  "Betis Sevilla II": 1297.0,
  "Cork City": 1298.0,
  "SC Wiedenbruck 2000": 1299.0,
  "ZFC Meuselwitz": 1300.0,
  "SS Monopoli": 1301.0,
  "Barry Town": 1302.0,
  "FC Spaeri": 1303.0,
  "Mladost Lucani": 1304.0,
  "PSV Eindhoven II": 1305.0,
  "FK Rudar Prijedor": 1306.0,
  "1. FK Pribram": 1307.0,
  "RFC Seresien": 1308.0,
  "KRC Genk II": 1309.0,
  "RSC Anderlecht II": 1310.0,
  "Helmond Sport": 1311.0,
  "Mjøndalen IF": 1312.0,
  "Unia Skierniewice": 1313.0,
  "Billericay Town FC": 1314.0,
  "Inter Milan II": 1315.0,
  "Vikingur Gotu": 1316.0,
  "Progres Niedercorn": 1317.0,
  "Colwyn Bay": 1318.0,
  "AS Cittadella": 1319.0,
  "Berrichonne Chateauroux": 1320.0,
  "Fremad Amager": 1321.0,
  "SK Sokol Zapy": 1322.0,
  "CD Trofense": 1323.0,
  "PFC Montana 1921": 1324.0,
  "Isparta 32 Spor": 1325.0,
  "Ullensaker/Kisa IL": 1326.0,
  "CS Afumati": 1327.0,
  "MP Mikkeli": 1328.0,
  "Erzincanspor": 1329.0,
  "KF Ferizaj": 1330.0,
  "ASKO Oedt": 1331.0,
  "Fotbal Pribram": 1332.0,
  "Kristianstads FF": 1333.0,
  "AEK Athens II": 1334.0,
  "ALS Omonia May 29": 1335.0,
  "FK Spartak Subotica": 1336.0,
  "PAOK Saloniki II": 1337.0,
  "Zaglebie Sosnowiec": 1338.0,
  "Ravenna FC 1913": 1339.0,
  "SC Imst": 1340.0,
  "Sparta Prague B": 1341.0,
  "Aubagne FC": 1342.0,
  "SV Spakenburg": 1343.0,
  "Lunds BK": 1344.0,
  "Sligo Rovers": 1345.0,
  "Perugia Calcio": 1346.0,
  "FK Fratria": 1347.0,
  "HNK Cibalia Vinkovci": 1348.0,
  "Bahlinger SC": 1349.0,
  "FC Metaloglobus Bukarest": 1350.0,
  "Walton & Hersham FC": 1351.0,
  "FC Santa Coloma": 1352.0,
  "FC Oss": 1353.0,
  "Sparta Praha II": 1354.0,
  "AD Marco 09": 1355.0,
  "TSV Schott Mainz": 1356.0,
  "AC Renate": 1357.0,
  "HSV Hoek": 1358.0,
  "FC Dornbirn": 1359.0,
  "Hednesford Town": 1360.0,
  "1.SK Prostejov": 1361.0,
  "Caernarfon Town": 1362.0,
  "Marine FC": 1363.0,
  "FC BiH Odense": 1364.0,
  "FK Turan Turkestan": 1365.0,
  "Ironi Beit Dagan": 1366.0,
  "Motala AIF FK": 1367.0,
  "AFC Gandra": 1368.0,
  "Aveley FC": 1369.0,
  "Chojniczanka Chojnice": 1370.0,
  "Hebburn Town": 1371.0,
  "Serik Belediyespor": 1372.0,
  "FC United of Manchester": 1373.0,
  "ASA Targu Mures": 1374.0,
  "Maccabi Jaffa": 1375.0,
  "Karacabey Belediyespor": 1376.0,
  "SV Oberwart": 1377.0,
  "Hapoel Hadera": 1378.0,
  "Decic Tuzi": 1379.0,
  "US Mondorf-les-Bains": 1380.0,
  "Casertana FC": 1381.0,
  "FC Rosengard": 1382.0,
  "Airdrieonians FC": 1383.0,
  "Napredak Krusevac": 1384.0,
  "FC Bnei Raanana": 1385.0,
  "Warta Poznan": 1386.0,
  "Hertha Zehlendorf": 1387.0,
  "Amarante FC": 1388.0,
  "IFK Haninge": 1389.0,
  "Stal Stalowa Wola": 1390.0,
  "Olimpia Grudziadz": 1391.0,
  "Podbeskidzie Bielsko Biala": 1392.0,
  "MS Kafr Kasem": 1393.0,
  "Sportovni Sdruzeni Ostra": 1394.0,
  "FC Podari": 1395.0,
  "Hapoel Ironi Bnei Ibillin": 1396.0,
  "Jiskra Domazlice": 1397.0,
  "Holbæk BK": 1398.0,
  "Hellerup IK": 1399.0,
  "NK Celik Zenica": 1400.0,
  "Alfreton Town": 1401.0,
  "Stockton Town FC": 1402.0,
  "Tabor Sezana": 1403.0,
  "Greenock Morton FC": 1404.0,
  "Dynamo Ceske Budejovice": 1405.0,
  "Olympic Charleroi": 1406.0,
  "Diyarbakirspor": 1407.0,
  "Altona 93": 1408.0,
  "Gloucester City": 1409.0,
  "Hapoel Nof Hagalil": 1410.0,
  "68 Aksaray Belediyespor": 1411.0,
  "Karlskrona AIF": 1412.0,
  "FK Kapaz": 1413.0,
  "Asteras Tripolis II": 1414.0,
  "Novara Calcio": 1415.0,
  "Calcio Lecco": 1416.0,
  "Queens Park": 1417.0,
  "Stade Briochin": 1418.0,
  "Caldas SC": 1419.0,
  "Sporting Braga II": 1420.0,
  "Stjoerdals-Blink": 1421.0,
  "FC Beitar Yavne": 1422.0,
  "Spennymoor Town": 1423.0,
  "IFK Stocksund": 1424.0,
  "Ingulets Petrovo": 1425.0,
  "Ragsveds IF": 1426.0,
  "SSD Siracusa Calcio": 1427.0,
  "FK AKAS Almaty": 1428.0,
  "Maccabi Akhi Arara": 1429.0,
  "FC Samtredia": 1430.0,
  "SR Donaufeld Wien": 1431.0,
  "Szeged 2011 FC": 1432.0,
  "IR Reykjavik": 1433.0,
  "Worksop Town": 1434.0,
  "FK Jelgava": 1435.0,
  "BK Forward Orebro": 1436.0,
  "GBK Kokkola": 1437.0,
  "Mezokovesdi SE": 1438.0,
  "CSM Poli Iasi": 1439.0,
  "SV Kuchl": 1440.0,
  "Birkirkara FC": 1441.0,
  "Celtic U20": 1442.0,
  "Fethiyespor": 1443.0,
  "Gainsborough Trinity": 1444.0,
  "NK Rudeš": 1445.0,
  "Nacka Iliria": 1446.0,
  "Sandecja Nowy Sacz": 1447.0,
  "GVVV Veenendaal": 1448.0,
  "Bashkimi Kumanovo": 1449.0,
  "Slough Town FC": 1450.0,
  "Excelsior Virton": 1451.0,
  "NK Stupcanica": 1452.0,
  "Atvidabergs FF": 1453.0,
  "Viktoria Aschaffenburg": 1454.0,
  "Real Bedford FC": 1455.0,
  "SSD Casarano Calcio": 1456.0,
  "SS Cavese": 1457.0,
  "Ajax Amsterdam II": 1458.0,
  "Tonbridge Angels": 1459.0,
  "Akademiya Ontystik": 1460.0,
  "Balzan Youths": 1461.0,
  "SV Horn": 1462.0,
  "SK Bischofshofen": 1463.0,
  "Mus Spor FC": 1464.0,
  "Thisted FC": 1465.0,
  "Eastbourne Borough": 1466.0,
  "Lahden Reipas": 1467.0,
  "Hampton and Richmond": 1468.0,
  "GIANA Erminio": 1469.0,
  "Menemen FK": 1470.0,
  "Cliftonville FC": 1471.0,
  "ACS FC Bacau": 1472.0,
  "Paris 13 Atletico": 1473.0,
  "SK Sigma Olomouc II": 1474.0,
  "UC Albinoleffe": 1475.0,
  "Olympia Wijgmaal": 1476.0,
  "Campobasso FC": 1477.0,
  "St. Albans City": 1478.0,
  "AC Milan II": 1479.0,
  "UD Santarem": 1480.0,
  "KPV Kokkola": 1481.0,
  "Bayern Alzenau": 1482.0,
  "Penybont FC": 1483.0,
  "HVV Te Werve": 1484.0,
  "NK Karlovac": 1485.0,
  "FK Pelister Bitola": 1486.0,
  "SC Bruhl SG": 1487.0,
  "FC Bourg Peronnas": 1488.0,
  "Cleethorpes Town": 1489.0,
  "Needham Market": 1490.0,
  "FC Chayka": 1491.0,
  "Alcione Milano": 1492.0,
  "Carrick Rangers": 1493.0,
  "US Latina Calcio": 1494.0,
  "Adana Demirspor": 1495.0,
  "AS Lucchese Libertas": 1496.0,
  "FK Siauliai": 1497.0,
  "Bedford Town FC": 1498.0,
  "KS Bylis Ballsh": 1499.0,
  "BK Olympic Malmo": 1500.0,
  "Spain": 2250.2,
  "Argentina": 2244.45,
  "Brazil": 2234.11,
  "France": 2225.47,
  "Portugal": 2153.88,
  "England": 2130.61,
  "Germany": 2106.26,
  "Colombia": 2100.22,
  "Netherlands": 2079.54,
  "Mexico": 2077.12,
  "Belgium": 2056.55,
  "Uruguay": 2053.24,
  "Ecuador": 2045.8,
  "Japan": 2029.24,
  "Italy": 2019.59,
  "Morocco": 2010.41,
  "Norway": 1998.71,
  "Denmark": 1992.35,
  "Switzerland": 1971.81,
  "USA": 1967.41,
  "Austria": 1964.91,
  "Paraguay": 1947.97,
  "South Korea": 1938.49,
  "Croatia": 1925.36,
  "Senegal": 1923.64,
  "Costa Rica": 1914.14,
  "Cote d'Ivoire": 1896.76,
  "Turkey": 1894.05,
  "Canada": 1889.76,
  "Chile": 1884.12,
  "Panama": 1877.78,
  "Bolivia": 1869.42,
  "Nigeria": 1869.08,
  "Sweden": 1866.35,
  "Scotland": 1864.34,
  "Iran": 1863.34,
  "Egypt": 1860.4,
  "Venezuela": 1858.16,
  "Australia": 1842.82,
  "Greece": 1839.9,
  "Poland": 1839.26,
  "Serbia": 1837.08,
  "Ukraine": 1826.98,
  "South Africa": 1825.43,
  "Czech Republic": 1821.47,
  "Hungary": 1818.94,
  "Haiti": 1815.28,
  "Algeria": 1813.28,
  "Slovakia": 1805.78,
  "Georgia": 1799.64,
  "Uzbekistan": 1797.99,
  "DR Congo": 1790.91,
  "Wales": 1787.15,
  "Cameroon": 1786.4,
  "Honduras": 1774.26,
  "Russia": 1770.16,
  "Ireland": 1766.62,
  "Romania": 1764.37,
  "Cape Verde": 1760.67,
  "Suriname": 1756.39,
  "Peru": 1755.91,
  "Tunisia": 1755.74,
  "Angola": 1753.2,
  "Jamaica": 1752.31,
  "Iceland": 1745.59,
  "Saudi Arabia": 1743.92,
  "Albania": 1738.78,
  "Burkina Faso": 1738.68,
  "Ghana": 1731.33,
  "Slovenia": 1725.38,
  "New Zealand": 1724.62,
  "Northern Ireland": 1723.76,
  "Kosovo": 1716.49,
  "Gabon": 1715.73,
  "Mali": 1706.68,
  "United Arab Emirates": 1702.59,
  "Curacao": 1698.58,
  "Jordan": 1698.57,
  "Israel": 1694.15,
  "Bosnia-Herzegovina": 1693.72,
  "Guatemala": 1693.53,
  "Dominican Republic": 1679.22,
  "North Macedonia": 1670.97,
  "Qatar": 1661.89,
  "Iraq": 1661.03,
  "Uganda": 1661.01,
  "Guinea": 1660.86,
  "Oman": 1653.84,
  "Montenegro": 1642.22,
  "Finland": 1619.45,
  "Indonesia": 1596.16,
  "Trinidad & Tobago": 1594.94,
  "Syria": 1594.07,
  "Luxembourg": 1589.84,
  "Madagascar": 1575.44,
  "Guadeloupe": 1573.49,
  "China": 1573.45,
  "Tanzania": 1572.32,
  "Equatorial Guinea": 1571.99,
  "El Salvador": 1568.58
}